setup.py
CydraHgWebdir.egg-info/PKG-INFO
CydraHgWebdir.egg-info/SOURCES.txt
CydraHgWebdir.egg-info/dependency_links.txt
CydraHgWebdir.egg-info/entry_points.txt
CydraHgWebdir.egg-info/namespace_packages.txt
CydraHgWebdir.egg-info/requires.txt
CydraHgWebdir.egg-info/top_level.txt
cydraplugins/__init__.py
cydraplugins/hgwebdir/__init__.py