Metadata-Version: 1.0
Name: CydraHgWebdir
Version: 0.2.0
Summary: Cydra plugin for hgwebdir
Home-page: http://www.cydra.org
Author: Manuel Stocker
Author-email: mensi@vis.ethz.ch
License: GPL
Keywords: cydra hgwebdir
Platform: UNKNOWN
